{
"meta":{"test_sets":[],"test_metrics":[],"learn_metrics":[{"best_value":"Min","name":"MultiQuantile:alpha=0.1,0.5,0.9"}],"launch_mode":"Train","parameters":"","iteration_count":300,"learn_sets":["learn"],"name":"experiment"},
"iterations":[
{"learn":[1.523987369],"iteration":0,"passed_time":0.02434921481,"remaining_time":7.280415229},
{"learn":[1.467252299],"iteration":1,"passed_time":0.08018851618,"remaining_time":11.94808891},
{"learn":[1.404898534],"iteration":2,"passed_time":0.1417999034,"remaining_time":14.03819043},
{"learn":[1.339295239],"iteration":3,"passed_time":0.1745654621,"remaining_time":12.91784419},
{"learn":[1.282541274],"iteration":4,"passed_time":0.2244451499,"remaining_time":13.24226385},
{"learn":[1.248402334],"iteration":5,"passed_time":0.287521797,"remaining_time":14.08856805},
{"learn":[1.206571028],"iteration":6,"passed_time":0.3346181712,"remaining_time":14.00616059},
{"learn":[1.176279705],"iteration":7,"passed_time":0.3627952224,"remaining_time":13.24202562},
{"learn":[1.147535908],"iteration":8,"passed_time":0.441527219,"remaining_time":14.27604675},
{"learn":[1.109940284],"iteration":9,"passed_time":0.5422506742,"remaining_time":15.72526955},
{"learn":[1.090809818],"iteration":10,"passed_time":0.604244537,"remaining_time":15.87515193},
{"learn":[1.061659648],"iteration":11,"passed_time":0.6879899585,"remaining_time":16.511759},
{"learn":[1.034033474],"iteration":12,"passed_time":0.7420263563,"remaining_time":16.38165879},
{"learn":[1.012958165],"iteration":13,"passed_time":0.7848743669,"remaining_time":16.03386207},
{"learn":[0.9903205174],"iteration":14,"passed_time":0.8269856774,"remaining_time":15.71272787},
{"learn":[0.9699940966],"iteration":15,"passed_time":0.8831277311,"remaining_time":15.67551723},
{"learn":[0.9530586118],"iteration":16,"passed_time":0.9346637066,"remaining_time":15.5594017},
{"learn":[0.9363920044],"iteration":17,"passed_time":0.9865541167,"remaining_time":15.45601449},
{"learn":[0.9141412344],"iteration":18,"passed_time":1.013943336,"remaining_time":14.99568828},
{"learn":[0.9019090406],"iteration":19,"passed_time":1.048386293,"remaining_time":14.6774081},
{"learn":[0.8911722664],"iteration":20,"passed_time":1.129054979,"remaining_time":15.00030186},
{"learn":[0.875790525],"iteration":21,"passed_time":1.19173959,"remaining_time":15.05925482},
{"learn":[0.8649407195],"iteration":22,"passed_time":1.22919596,"remaining_time":14.80379482},
{"learn":[0.8515172434],"iteration":23,"passed_time":1.273608855,"remaining_time":14.64650183},
{"learn":[0.8425603201],"iteration":24,"passed_time":1.309734201,"remaining_time":14.40707621},
{"learn":[0.8344249805],"iteration":25,"passed_time":1.338272066,"remaining_time":14.1033287},
{"learn":[0.8223399883],"iteration":26,"passed_time":1.391427268,"remaining_time":14.06887571},
{"learn":[0.8132754783],"iteration":27,"passed_time":1.453899221,"remaining_time":14.12359243},
{"learn":[0.8044298939],"iteration":28,"passed_time":1.496349615,"remaining_time":13.98312916},
{"learn":[0.7951969718],"iteration":29,"passed_time":1.55814878,"remaining_time":14.02333902},
{"learn":[0.7875492811],"iteration":30,"passed_time":1.605552777,"remaining_time":13.93205474},
{"learn":[0.7803609851],"iteration":31,"passed_time":1.664738495,"remaining_time":13.94218489},
{"learn":[0.7761365523],"iteration":32,"passed_time":1.697727322,"remaining_time":13.73615743},
{"learn":[0.76714565],"iteration":33,"passed_time":1.735977105,"remaining_time":13.58146794},
{"learn":[0.7634901754],"iteration":34,"passed_time":1.787536212,"remaining_time":13.53420275},
{"learn":[0.7589783142],"iteration":35,"passed_time":1.859171178,"remaining_time":13.63392197},
{"learn":[0.7521991847],"iteration":36,"passed_time":1.89740374,"remaining_time":13.48695091},
{"learn":[0.7506642544],"iteration":37,"passed_time":1.941219201,"remaining_time":13.38419554},
{"learn":[0.746503717],"iteration":38,"passed_time":1.981186803,"remaining_time":13.25871168},
{"learn":[0.742814041],"iteration":39,"passed_time":2.020190897,"remaining_time":13.13124083},
{"learn":[0.7396664755],"iteration":40,"passed_time":2.040138592,"remaining_time":12.88770476},
{"learn":[0.7344527116],"iteration":41,"passed_time":2.071012583,"remaining_time":12.72193444},
{"learn":[0.7310380846],"iteration":42,"passed_time":2.117572746,"remaining_time":12.6561906},
{"learn":[0.7299864107],"iteration":43,"passed_time":2.128315315,"remaining_time":12.38292547},
{"learn":[0.7260371128],"iteration":44,"passed_time":2.165189171,"remaining_time":12.2694053},
{"learn":[0.7188831405],"iteration":45,"passed_time":2.210815395,"remaining_time":12.20754588},
{"learn":[0.7144528666],"iteration":46,"passed_time":2.238952525,"remaining_time":12.0522338},
{"learn":[0.7113482531],"iteration":47,"passed_time":2.353694713,"remaining_time":12.35689724},
{"learn":[0.7058784533],"iteration":48,"passed_time":2.417783481,"remaining_time":12.38497253},
{"learn":[0.7020186976],"iteration":49,"passed_time":2.486582112,"remaining_time":12.43291056},
{"learn":[0.6985133805],"iteration":50,"passed_time":2.558571083,"remaining_time":12.49184705},
{"learn":[0.6953024794],"iteration":51,"passed_time":2.60109613,"remaining_time":12.4052277},
{"learn":[0.6897718712],"iteration":52,"passed_time":2.637861913,"remaining_time":12.29343193},
{"learn":[0.686368019],"iteration":53,"passed_time":2.689666269,"remaining_time":12.25292411},
{"learn":[0.683082911],"iteration":54,"passed_time":2.739356239,"remaining_time":12.20258688},
{"learn":[0.6800442914],"iteration":55,"passed_time":2.771518893,"remaining_time":12.07590375},
{"learn":[0.6776555589],"iteration":56,"passed_time":2.828371646,"remaining_time":12.05779491},
{"learn":[0.6731906134],"iteration":57,"passed_time":2.877617168,"remaining_time":12.00660956},
{"learn":[0.6706889029],"iteration":58,"passed_time":2.914059517,"remaining_time":11.90319226},
{"learn":[0.6694394388],"iteration":59,"passed_time":2.984427762,"remaining_time":11.93771105},
{"learn":[0.6658674775],"iteration":60,"passed_time":3.041862768,"remaining_time":11.91811806},
{"learn":[0.6642683937],"iteration":61,"passed_time":3.133150058,"remaining_time":12.02725345},
{"learn":[0.6628732756],"iteration":62,"passed_time":3.172887012,"remaining_time":11.93609876},
{"learn":[0.6607875785],"iteration":63,"passed_time":3.246404215,"remaining_time":11.97111554},
{"learn":[0.6594146277],"iteration":64,"passed_time":3.304108503,"remaining_time":11.94562305},
{"learn":[0.6576554383],"iteration":65,"passed_time":3.339979158,"remaining_time":11.84174429},
{"learn":[0.6553880361],"iteration":66,"passed_time":3.39239043,"remaining_time":11.79741746},
{"learn":[0.6523287123],"iteration":67,"passed_time":3.446841864,"remaining_time":11.75981342},
{"learn":[0.6497126769],"iteration":68,"passed_time":3.496806006,"remaining_time":11.70669837},
{"learn":[0.6465537749],"iteration":69,"passed_time":3.582213625,"remaining_time":11.77013048},
{"learn":[0.6445298942],"iteration":70,"passed_time":3.625804886,"remaining_time":11.69449745},
{"learn":[0.642052571],"iteration":71,"passed_time":3.670729861,"remaining_time":11.62397789},
{"learn":[0.6376052877],"iteration":72,"passed_time":3.707079937,"remaining_time":11.52749515},
{"learn":[0.6359126519],"iteration":73,"passed_time":3.770369032,"remaining_time":11.51491083},
{"learn":[0.6336621931],"iteration":74,"passed_time":3.815243456,"remaining_time":11.44573037},
{"learn":[0.632133119],"iteration":75,"passed_time":3.862408073,"remaining_time":11.38393958},
{"learn":[0.6297192873],"iteration":76,"passed_time":3.899653844,"remaining_time":11.29380269},
{"learn":[0.6279650297],"iteration":77,"passed_time":3.93896083,"remaining_time":11.21088852},
{"learn":[0.6260064378],"iteration":78,"passed_time":3.989792857,"remaining_time":11.16131926},
{"learn":[0.6251674651],"iteration":79,"passed_time":4.020264912,"remaining_time":11.05572851},
{"learn":[0.6234715562],"iteration":80,"passed_time":4.057280614,"remaining_time":10.96968462},
{"learn":[0.6225814775],"iteration":81,"passed_time":4.096633172,"remaining_time":10.89104917},
{"learn":[0.6214216913],"iteration":82,"passed_time":4.125728281,"remaining_time":10.78654261},
{"learn":[0.6200401529],"iteration":83,"passed_time":4.153999806,"remaining_time":10.68171379},
{"learn":[0.6195232167],"iteration":84,"passed_time":4.206141186,"remaining_time":10.639063},
{"learn":[0.618241364],"iteration":85,"passed_time":4.232967732,"remaining_time":10.53319878},
{"learn":[0.6167125643],"iteration":86,"passed_time":4.255936081,"remaining_time":10.41970558},
{"learn":[0.6148921712],"iteration":87,"passed_time":4.323040762,"remaining_time":10.4145982},
{"learn":[0.6138529914],"iteration":88,"passed_time":4.362731874,"remaining_time":10.3431059},
{"learn":[0.61185029],"iteration":89,"passed_time":4.40743034,"remaining_time":10.28400413},
{"learn":[0.6107479847],"iteration":90,"passed_time":4.46397709,"remaining_time":10.2524309},
{"learn":[0.6093873879],"iteration":91,"passed_time":4.532546772,"remaining_time":10.24749705},
{"learn":[0.6073575446],"iteration":92,"passed_time":4.573942863,"remaining_time":10.18071153},
{"learn":[0.604882294],"iteration":93,"passed_time":4.59737453,"remaining_time":10.07509738},
{"learn":[0.6035907745],"iteration":94,"passed_time":4.62747593,"remaining_time":9.985605955},
{"learn":[0.6025973184],"iteration":95,"passed_time":4.661637356,"remaining_time":9.905979382},
{"learn":[0.6013484616],"iteration":96,"passed_time":4.712438822,"remaining_time":9.862114235},
{"learn":[0.5998896657],"iteration":97,"passed_time":4.791970621,"remaining_time":9.877327198},
{"learn":[0.598625167],"iteration":98,"passed_time":4.831192533,"remaining_time":9.80878484},
{"learn":[0.5974568176],"iteration":99,"passed_time":4.868033969,"remaining_time":9.736067937},
{"learn":[0.5946300658],"iteration":100,"passed_time":4.964442827,"remaining_time":9.781426957},
{"learn":[0.5936958106],"iteration":101,"passed_time":4.994404702,"remaining_time":9.695020891},
{"learn":[0.5928728594],"iteration":102,"passed_time":5.017531746,"remaining_time":9.596638389},
{"learn":[0.5916173871],"iteration":103,"passed_time":5.072065074,"remaining_time":9.558891871},
{"learn":[0.5902071903],"iteration":104,"passed_time":5.130755942,"remaining_time":9.52854675},
{"learn":[0.5891993254],"iteration":105,"passed_time":5.165584615,"remaining_time":9.453994485},
{"learn":[0.586721253],"iteration":106,"passed_time":5.228199853,"remaining_time":9.430304409},
{"learn":[0.5853320961],"iteration":107,"passed_time":5.272467422,"remaining_time":9.373275417},
{"learn":[0.5848717175],"iteration":108,"passed_time":5.327540122,"remaining_time":9.335414342},
{"learn":[0.5841100385],"iteration":109,"passed_time":5.361961278,"remaining_time":9.261569481},
{"learn":[0.5829086697],"iteration":110,"passed_time":5.38795032,"remaining_time":9.174077572},
{"learn":[0.5815460967],"iteration":111,"passed_time":5.421890557,"remaining_time":9.101030578},
{"learn":[0.5804705793],"iteration":112,"passed_time":5.455657537,"remaining_time":9.028389021},
{"learn":[0.5773354997],"iteration":113,"passed_time":5.511696746,"remaining_time":8.992768375},
{"learn":[0.5754838576],"iteration":114,"passed_time":5.559252059,"remaining_time":8.943144617},
{"learn":[0.5742117893],"iteration":115,"passed_time":5.60136434,"remaining_time":8.884922745},
{"learn":[0.5731762389],"iteration":116,"passed_time":5.617673506,"remaining_time":8.786617535},
{"learn":[0.5712227275],"iteration":117,"passed_time":5.642236259,"remaining_time":8.702432197},
{"learn":[0.5693218976],"iteration":118,"passed_time":5.692692481,"remaining_time":8.658633101},
{"learn":[0.5674943353],"iteration":119,"passed_time":5.739600517,"remaining_time":8.609400776},
{"learn":[0.566071695],"iteration":120,"passed_time":5.790977956,"remaining_time":8.56681863},
{"learn":[0.56427981],"iteration":121,"passed_time":5.840175306,"remaining_time":8.520911513},
{"learn":[0.5629643349],"iteration":122,"passed_time":5.877926209,"remaining_time":8.458479178},
{"learn":[0.5614243516],"iteration":123,"passed_time":5.941091899,"remaining_time":8.432517535},
{"learn":[0.5605685692],"iteration":124,"passed_time":5.945082762,"remaining_time":8.323115867},
{"learn":[0.5598034344],"iteration":125,"passed_time":5.976563509,"remaining_time":8.253349607},
{"learn":[0.5587720914],"iteration":126,"passed_time":6.025103022,"remaining_time":8.207423801},
{"learn":[0.5581639829],"iteration":127,"passed_time":6.081613011,"remaining_time":8.172167483},
{"learn":[0.5565825923],"iteration":128,"passed_time":6.140874132,"remaining_time":8.1402285},
{"learn":[0.5553991075],"iteration":129,"passed_time":6.227864846,"remaining_time":8.144130952},
{"learn":[0.5545640725],"iteration":130,"passed_time":6.265216722,"remaining_time":8.082607832},
{"learn":[0.5540921519],"iteration":131,"passed_time":6.376487598,"remaining_time":8.11552967},
{"learn":[0.553653484],"iteration":132,"passed_time":6.410246937,"remaining_time":8.048956681},
{"learn":[0.5520198255],"iteration":133,"passed_time":6.453366079,"remaining_time":7.994468426},
{"learn":[0.550352668],"iteration":134,"passed_time":6.50478381,"remaining_time":7.950291323},
{"learn":[0.5493352352],"iteration":135,"passed_time":6.548100029,"remaining_time":7.896238271},
{"learn":[0.5475928028],"iteration":136,"passed_time":6.583556328,"remaining_time":7.832990376},
{"learn":[0.5471046313],"iteration":137,"passed_time":6.606897762,"remaining_time":7.755923459},
{"learn":[0.5458802621],"iteration":138,"passed_time":6.654760277,"remaining_time":7.708031688},
{"learn":[0.5451940385],"iteration":139,"passed_time":6.687681612,"remaining_time":7.6430647},
{"learn":[0.5435342092],"iteration":140,"passed_time":6.721266564,"remaining_time":7.579300594},
{"learn":[0.5424172877],"iteration":141,"passed_time":6.784522669,"remaining_time":7.548975927},
{"learn":[0.5414136386],"iteration":142,"passed_time":6.8148953,"remaining_time":7.482087846},
{"learn":[0.5404415039],"iteration":143,"passed_time":6.83742317,"remaining_time":7.407208434},
{"learn":[0.539423924],"iteration":144,"passed_time":6.867228718,"remaining_time":7.340830698},
{"learn":[0.5380317389],"iteration":145,"passed_time":6.899923483,"remaining_time":7.278001483},
{"learn":[0.5374943496],"iteration":146,"passed_time":6.936715967,"remaining_time":7.219847231},
{"learn":[0.5357781699],"iteration":147,"passed_time":6.970149643,"remaining_time":7.158532065},
{"learn":[0.5344288442],"iteration":148,"passed_time":7.007327282,"remaining_time":7.101385366},
{"learn":[0.5333882193],"iteration":149,"passed_time":7.030730428,"remaining_time":7.030730428},
{"learn":[0.5326763772],"iteration":150,"passed_time":7.058966841,"remaining_time":6.965470592},
{"learn":[0.5316549974],"iteration":151,"passed_time":7.092503782,"remaining_time":6.905858945},
{"learn":[0.5305156893],"iteration":152,"passed_time":7.128657159,"remaining_time":6.849101976},
{"learn":[0.5297891301],"iteration":153,"passed_time":7.164645029,"remaining_time":6.792455677},
{"learn":[0.5291514385],"iteration":154,"passed_time":7.202453874,"remaining_time":6.73777943},
{"learn":[0.5277842024],"iteration":155,"passed_time":7.255022371,"remaining_time":6.696943727},
{"learn":[0.5265102174],"iteration":156,"passed_time":7.300927547,"remaining_time":6.649889422},
{"learn":[0.524805146],"iteration":157,"passed_time":7.340621399,"remaining_time":6.597267333},
{"learn":[0.5239083298],"iteration":158,"passed_time":7.391827851,"remaining_time":6.555017151},
{"learn":[0.5228332748],"iteration":159,"passed_time":7.427483567,"remaining_time":6.499048122},
{"learn":[0.5218741202],"iteration":160,"passed_time":7.481291936,"remaining_time":6.459003597},
{"learn":[0.5211467787],"iteration":161,"passed_time":7.509225377,"remaining_time":6.396747543},
{"learn":[0.5195432081],"iteration":162,"passed_time":7.550881969,"remaining_time":6.346446808},
{"learn":[0.517735532],"iteration":163,"passed_time":7.587683053,"remaining_time":6.29222497},
{"learn":[0.5168924716],"iteration":164,"passed_time":7.639640995,"remaining_time":6.25061536},
{"learn":[0.5154361142],"iteration":165,"passed_time":7.675944549,"remaining_time":6.196244395},
{"learn":[0.5138207784],"iteration":166,"passed_time":7.731873274,"remaining_time":6.157719434},
{"learn":[0.5119921849],"iteration":167,"passed_time":7.776795219,"remaining_time":6.110339101},
{"learn":[0.511575578],"iteration":168,"passed_time":7.809686353,"remaining_time":6.053662202},
{"learn":[0.5111723417],"iteration":169,"passed_time":7.85613416,"remaining_time":6.007632005},
{"learn":[0.5092590633],"iteration":170,"passed_time":7.893736707,"remaining_time":5.954924182},
{"learn":[0.5084886681],"iteration":171,"passed_time":7.916976016,"remaining_time":5.891703082},
{"learn":[0.5079780894],"iteration":172,"passed_time":7.950882321,"remaining_time":5.836774883},
{"learn":[0.5070967135],"iteration":173,"passed_time":8.010252147,"remaining_time":5.800527417},
{"learn":[0.5064813924],"iteration":174,"passed_time":8.046124943,"remaining_time":5.747232102},
{"learn":[0.5059376802],"iteration":175,"passed_time":8.067654222,"remaining_time":5.684029111},
{"learn":[0.504650226],"iteration":176,"passed_time":8.103048488,"remaining_time":5.630932},
{"learn":[0.5037098855],"iteration":177,"passed_time":8.14543084,"remaining_time":5.582823385},
{"learn":[0.5031649257],"iteration":178,"passed_time":8.180594267,"remaining_time":5.529898918},
{"learn":[0.5019466261],"iteration":179,"passed_time":8.221232387,"remaining_time":5.480821591},
{"learn":[0.5014014518],"iteration":180,"passed_time":8.262109627,"remaining_time":5.431994727},
{"learn":[0.4999806861],"iteration":181,"passed_time":8.309862708,"remaining_time":5.387713184},
{"learn":[0.4988889913],"iteration":182,"passed_time":8.384931695,"remaining_time":5.360857969},
{"learn":[0.4977086606],"iteration":183,"passed_time":8.429274867,"remaining_time":5.314108068},
{"learn":[0.4971853089],"iteration":184,"passed_time":8.474735664,"remaining_time":5.268078926},
{"learn":[0.4964914204],"iteration":185,"passed_time":8.522107489,"remaining_time":5.223227171},
{"learn":[0.4961129516],"iteration":186,"passed_time":8.562182357,"remaining_time":5.173939071},
{"learn":[0.4948601032],"iteration":187,"passed_time":8.594745757,"remaining_time":5.120274068},
{"learn":[0.493524685],"iteration":188,"passed_time":8.625454032,"remaining_time":5.065742844},
{"learn":[0.4921739086],"iteration":189,"passed_time":8.662139191,"remaining_time":5.014922689},
{"learn":[0.4915248396],"iteration":190,"passed_time":8.696236234,"remaining_time":4.962773557},
{"learn":[0.4905172599],"iteration":191,"passed_time":8.735898394,"remaining_time":4.913942847},
{"learn":[0.4893559363],"iteration":192,"passed_time":8.768244446,"remaining_time":4.861151066},
{"learn":[0.4889584866],"iteration":193,"passed_time":8.800314596,"remaining_time":4.808419315},
{"learn":[0.4881035951],"iteration":194,"passed_time":8.839105371,"remaining_time":4.759518277},
{"learn":[0.4871534227],"iteration":195,"passed_time":8.89023719,"remaining_time":4.717268713},
{"learn":[0.4865360384],"iteration":196,"passed_time":8.948565503,"remaining_time":4.678691608},
{"learn":[0.4858612912],"iteration":197,"passed_time":9.007397186,"remaining_time":4.640174308},
{"learn":[0.4850660864],"iteration":198,"passed_time":9.081819167,"remaining_time":4.609365507},
{"learn":[0.4839786367],"iteration":199,"passed_time":9.131158113,"remaining_time":4.565579056},
{"learn":[0.4837967063],"iteration":200,"passed_time":9.199452203,"remaining_time":4.531073473},
{"learn":[0.4828830769],"iteration":201,"passed_time":9.236446285,"remaining_time":4.481048197},
{"learn":[0.4821740992],"iteration":202,"passed_time":9.335100645,"remaining_time":4.460614594},
{"learn":[0.4807885328],"iteration":203,"passed_time":9.403213888,"remaining_time":4.42504183},
{"learn":[0.4802622084],"iteration":204,"passed_time":9.442996553,"remaining_time":4.376022793},
{"learn":[0.4785255591],"iteration":205,"passed_time":9.653149829,"remaining_time":4.404835359},
{"learn":[0.4780497885],"iteration":206,"passed_time":9.707060722,"remaining_time":4.361143223},
{"learn":[0.4773098052],"iteration":207,"passed_time":9.817908801,"remaining_time":4.342536585},
{"learn":[0.4766698492],"iteration":208,"passed_time":9.888530326,"remaining_time":4.305532343},
{"learn":[0.4761215174],"iteration":209,"passed_time":9.967091486,"remaining_time":4.271610637},
{"learn":[0.4753979885],"iteration":210,"passed_time":10.00643079,"remaining_time":4.220721993},
{"learn":[0.4739748355],"iteration":211,"passed_time":10.07740654,"remaining_time":4.183074414},
{"learn":[0.4733695472],"iteration":212,"passed_time":10.18499374,"remaining_time":4.160067865},
{"learn":[0.4725223059],"iteration":213,"passed_time":10.23593288,"remaining_time":4.113505737},
{"learn":[0.4722732129],"iteration":214,"passed_time":10.31797437,"remaining_time":4.07919917},
{"learn":[0.4711849965],"iteration":215,"passed_time":10.39018074,"remaining_time":4.040625844},
{"learn":[0.4706857514],"iteration":216,"passed_time":10.48373858,"remaining_time":4.009909228},
{"learn":[0.4701444446],"iteration":217,"passed_time":10.57112382,"remaining_time":3.976294282},
{"learn":[0.4696338538],"iteration":218,"passed_time":10.64248955,"remaining_time":3.936263258},
{"learn":[0.4694142595],"iteration":219,"passed_time":10.79284383,"remaining_time":3.924670485},
{"learn":[0.4686365457],"iteration":220,"passed_time":10.9546928,"remaining_time":3.915930909},
{"learn":[0.4678702312],"iteration":221,"passed_time":11.02436417,"remaining_time":3.87342525},
{"learn":[0.467094992],"iteration":222,"passed_time":11.09788284,"remaining_time":3.832004387},
{"learn":[0.4665548065],"iteration":223,"passed_time":11.12733096,"remaining_time":3.775344432},
{"learn":[0.4663223473],"iteration":224,"passed_time":11.20049374,"remaining_time":3.733497913},
{"learn":[0.4649059688],"iteration":225,"passed_time":11.29188077,"remaining_time":3.697341492},
{"learn":[0.4638620088],"iteration":226,"passed_time":11.4001324,"remaining_time":3.666121874},
{"learn":[0.4628475195],"iteration":227,"passed_time":11.53831983,"remaining_time":3.643679946},
{"learn":[0.4623837907],"iteration":228,"passed_time":11.56651968,"remaining_time":3.58612619},
{"learn":[0.4616206242],"iteration":229,"passed_time":11.62532823,"remaining_time":3.538143376},
{"learn":[0.4609486218],"iteration":230,"passed_time":11.66201708,"remaining_time":3.483459648},
{"learn":[0.4602958488],"iteration":231,"passed_time":11.80359549,"remaining_time":3.45967454},
{"learn":[0.459750914],"iteration":232,"passed_time":11.84886494,"remaining_time":3.407184338},
{"learn":[0.4591278436],"iteration":233,"passed_time":11.88050235,"remaining_time":3.350910919},
{"learn":[0.4588815164],"iteration":234,"passed_time":11.89882493,"remaining_time":3.291164342},
{"learn":[0.4585157127],"iteration":235,"passed_time":11.94130457,"remaining_time":3.238319885},
{"learn":[0.4581041589],"iteration":236,"passed_time":11.96991032,"remaining_time":3.181874896},
{"learn":[0.4572531851],"iteration":237,"passed_time":12.01936306,"remaining_time":3.13109458},
{"learn":[0.4570163881],"iteration":238,"passed_time":12.05825414,"remaining_time":3.077629718},
{"learn":[0.4565164593],"iteration":239,"passed_time":12.10319974,"remaining_time":3.025799935},
{"learn":[0.4562486843],"iteration":240,"passed_time":12.16587976,"remaining_time":2.978368904},
{"learn":[0.4558702346],"iteration":241,"passed_time":12.20482139,"remaining_time":2.925122482},
{"learn":[0.4554402213],"iteration":242,"passed_time":12.24566252,"remaining_time":2.872439356},
{"learn":[0.4545905407],"iteration":243,"passed_time":12.28024308,"remaining_time":2.818416445},
{"learn":[0.4539459631],"iteration":244,"passed_time":12.32974661,"remaining_time":2.767902301},
{"learn":[0.4535055484],"iteration":245,"passed_time":12.37178872,"remaining_time":2.7157585},
{"learn":[0.4525294931],"iteration":246,"passed_time":12.39945613,"remaining_time":2.660612045},
{"learn":[0.4518907567],"iteration":247,"passed_time":12.43727328,"remaining_time":2.607815365},
{"learn":[0.4507023221],"iteration":248,"passed_time":12.54629077,"remaining_time":2.569722206},
{"learn":[0.4497845244],"iteration":249,"passed_time":12.59954586,"remaining_time":2.519909171},
{"learn":[0.4486812909],"iteration":250,"passed_time":12.64666438,"remaining_time":2.468870736},
{"learn":[0.4481972394],"iteration":251,"passed_time":12.66690763,"remaining_time":2.41274431},
{"learn":[0.4480837221],"iteration":252,"passed_time":12.69997962,"remaining_time":2.359284752},
{"learn":[0.4477891357],"iteration":253,"passed_time":12.73022259,"remaining_time":2.305473382},
{"learn":[0.447493448],"iteration":254,"passed_time":12.76761653,"remaining_time":2.2531088},
{"learn":[0.4467173136],"iteration":255,"passed_time":12.81465372,"remaining_time":2.202518607},
{"learn":[0.4464045141],"iteration":256,"passed_time":12.86863557,"remaining_time":2.153118014},
{"learn":[0.4459929586],"iteration":257,"passed_time":12.91270929,"remaining_time":2.102068955},
{"learn":[0.4454402655],"iteration":258,"passed_time":12.94498977,"remaining_time":2.049206875},
{"learn":[0.4446688275],"iteration":259,"passed_time":12.9919808,"remaining_time":1.998766277},
{"learn":[0.4441710716],"iteration":260,"passed_time":13.04148713,"remaining_time":1.948727962},
{"learn":[0.4437386529],"iteration":261,"passed_time":13.06572598,"remaining_time":1.895028959},
{"learn":[0.4427425724],"iteration":262,"passed_time":13.10353687,"remaining_time":1.843463362},
{"learn":[0.4423581672],"iteration":263,"passed_time":13.14593563,"remaining_time":1.792627586},
{"learn":[0.4418852259],"iteration":264,"passed_time":13.19519728,"remaining_time":1.742761905},
{"learn":[0.4414259255],"iteration":265,"passed_time":13.24145427,"remaining_time":1.692516712},
{"learn":[0.4409136833],"iteration":266,"passed_time":13.26887286,"remaining_time":1.639973051},
{"learn":[0.4403427311],"iteration":267,"passed_time":13.29445908,"remaining_time":1.587398099},
{"learn":[0.4396557131],"iteration":268,"passed_time":13.39938499,"remaining_time":1.544167043},
{"learn":[0.4394617683],"iteration":269,"passed_time":13.44268972,"remaining_time":1.493632192},
{"learn":[0.4386849079],"iteration":270,"passed_time":13.48008716,"remaining_time":1.442518552},
{"learn":[0.4378799556],"iteration":271,"passed_time":13.51723556,"remaining_time":1.391480131},
{"learn":[0.4373939867],"iteration":272,"passed_time":13.53582702,"remaining_time":1.338708167},
{"learn":[0.4370633945],"iteration":273,"passed_time":13.57709942,"remaining_time":1.288337901},
{"learn":[0.4367358082],"iteration":274,"passed_time":13.60212129,"remaining_time":1.236556481},
{"learn":[0.4358892145],"iteration":275,"passed_time":13.63948626,"remaining_time":1.186042283},
{"learn":[0.4355922894],"iteration":276,"passed_time":13.68677315,"remaining_time":1.136446868},
{"learn":[0.4350933168],"iteration":277,"passed_time":13.7312568,"remaining_time":1.086646222},
{"learn":[0.4347544006],"iteration":278,"passed_time":13.78562508,"remaining_time":1.037627694},
{"learn":[0.4343053517],"iteration":279,"passed_time":13.81511831,"remaining_time":0.9867941651},
{"learn":[0.4339996714],"iteration":280,"passed_time":13.85052984,"remaining_time":0.9365126937},
{"learn":[0.4334969145],"iteration":281,"passed_time":14.00967679,"remaining_time":0.8942346887},
{"learn":[0.4328763537],"iteration":282,"passed_time":14.11107374,"remaining_time":0.8476616736},
{"learn":[0.4321175346],"iteration":283,"passed_time":14.23025462,"remaining_time":0.8017044857},
{"learn":[0.4317393024],"iteration":284,"passed_time":14.39218608,"remaining_time":0.7574834778},
{"learn":[0.4313536812],"iteration":285,"passed_time":14.47789264,"remaining_time":0.7087080313},
{"learn":[0.4310852037],"iteration":286,"passed_time":14.56867707,"remaining_time":0.6599052331},
{"learn":[0.4309034507],"iteration":287,"passed_time":14.62227527,"remaining_time":0.6092614695},
{"learn":[0.4305948491],"iteration":288,"passed_time":14.68476398,"remaining_time":0.5589356533},
{"learn":[0.4300244369],"iteration":289,"passed_time":14.71989984,"remaining_time":0.507582753},
{"learn":[0.4295594654],"iteration":290,"passed_time":14.75526821,"remaining_time":0.4563485014},
{"learn":[0.4286701114],"iteration":291,"passed_time":14.8075317,"remaining_time":0.4056857999},
{"learn":[0.4283160639],"iteration":292,"passed_time":14.83713911,"remaining_time":0.3544709002},
{"learn":[0.4269981116],"iteration":293,"passed_time":14.8792664,"remaining_time":0.3036584979},
{"learn":[0.4265974898],"iteration":294,"passed_time":14.9225031,"remaining_time":0.2529237814},
{"learn":[0.4264556484],"iteration":295,"passed_time":14.96484417,"remaining_time":0.202227624},
{"learn":[0.4262868024],"iteration":296,"passed_time":14.99578065,"remaining_time":0.1514725318},
{"learn":[0.4258454416],"iteration":297,"passed_time":15.02937166,"remaining_time":0.1008682662},
{"learn":[0.4250222751],"iteration":298,"passed_time":15.07503033,"remaining_time":0.05041816163},
{"learn":[0.4244532477],"iteration":299,"passed_time":15.10995192,"remaining_time":0}
]}