{
  "date": "2026-04-26",
  "day": "sunday",
  "comment": "14-й прогон (вс 19:29-19:32, evening слот). 11 заказов из ОДНОЙ опорной точки М.Богдановича 70 (СВ центр) во все стороны Минска — лучевой замер для оценки ⚡-карты в воскресный вечер. Диапазон ⚡ от 1.0 (короткий 0.6 км до Шевченко 11) до 2.6 (длинный 26 мин до Слободского пр-да). Все intra-Минск. Эконом ⚡ скрыт у всех — оценка через factE/0.952 ≈ Cmf-уровень.",
  "coords": {
    "Максима Богдановича 70":   [53.92411, 27.57062],
    "Слободской пр-д 6":        [53.84949, 27.44318],
    "Долгобродская 56":         [53.89898, 27.60600],
    "Нововиленская 55":         [53.93674, 27.53031],
    "Тикоцкого 2А":             [53.95459, 27.63158],
    "2-й пер. Кольцова 8":      [53.95129, 27.59964],
    "б-р Шевченко 11":          [53.92729, 27.55557],
    "Кирилла и Мефодия 8Б":     [53.90525, 27.55675],
    "Масюковщина 65А":          [53.92972, 27.45801],
    "Корженевского 20к1":       [53.84562, 27.50362],
    "Красноармейская 34Б":      [53.90257, 27.56577],
    "Коржа 16":                 [53.89529, 27.52087]
  },
  "orders": [
    { "id": "9917", "from": "Максима Богдановича 70", "to": "Слободской пр-д 6",
      "factE": 22.8, "factC": 25.5, "yaSurgeC": 2.6, "yaMin": 26, "hour": 19,
      "notes": "ЮВ через центр, прибытие 20:03 (26 мин). Cmf ⚡2.6 ОТКРЫТ. Электро ⚡2.6, К+ ⚡2.7, Биз ⚡3.6. Самый длинный заказ в пакете." },

    { "id": "9918", "from": "Максима Богдановича 70", "to": "Долгобродская 56",
      "factE": 16.3, "factC": 18.2, "yaSurgeC": 1.9, "yaMin": 18, "hour": 19,
      "notes": "ЮВ Заводской район, прибытие 19:52 (18 мин). Cmf ⚡1.9 ОТКРЫТ. Электро ⚡1.9, К+ ⚡2, Биз ⚡2.3." },

    { "id": "9919", "from": "Максима Богдановича 70", "to": "Нововиленская 55",
      "factE": 12.1, "factC": 13.8, "yaSurgeC": 1.4, "yaMin": 11, "hour": 19,
      "notes": "С через центр, прибытие 19:49 (11 мин). Cmf ⚡ скрыт (factC=13.8 → ≈⚡1.40). Электро ⚡1.4, К+ ⚡1.5, Биз ⚡1.6." },

    { "id": "9920", "from": "Максима Богдановича 70", "to": "Тикоцкого 2А",
      "factE": 14.1, "factC": 15.5, "yaSurgeC": 1.6, "yaMin": 14, "hour": 19,
      "notes": "СВ Уручье, прибытие 19:47 (14 мин). Cmf ⚡1.6 ОТКРЫТ. Электро ⚡1.6, К+ ⚡1.7, Биз ⚡1.9." },

    { "id": "9921", "from": "Максима Богдановича 70", "to": "2-й пер. Кольцова 8",
      "factE": 11.3, "factC": 12.8, "yaSurgeC": 1.3, "yaMin": 9, "hour": 19,
      "notes": "СВ Уручье ближний, прибытие 19:41 (9 мин). Cmf ⚡1.3 ОТКРЫТ. Электро ⚡1.3, К+ ⚡1.4, Биз ⚡1.5." },

    { "id": "9922", "from": "Максима Богдановича 70", "to": "б-р Шевченко 11",
      "factE": 9.0, "factC": 10.0, "yaSurgeC": 1.0, "yaMin": 5, "hour": 19,
      "notes": "Очень близкий заказ (5 мин), прибытие 19:37. Cmf ⚡ скрыт (factC=10 → ⚡1.01). Электро ⚡1.1, К+ ⚡1.1, Биз ⚡1.4. Минимальная цена baseline." },

    { "id": "9923", "from": "Максима Богдановича 70", "to": "Кирилла и Мефодия 8Б",
      "factE": 12.0, "factC": 13.7, "yaSurgeC": 1.4, "yaMin": 14, "hour": 19,
      "notes": "Ю через центр и Немигу, прибытие 19:50 (14 мин). Cmf ⚡1.4 ОТКРЫТ. Электро ⚡1.4, К+ ⚡1.5, Биз ⚡1.6." },

    { "id": "9924", "from": "Максима Богдановича 70", "to": "Масюковщина 65А",
      "factE": 18.1, "factC": 20.0, "yaSurgeC": 2.0, "yaMin": 21, "hour": 19,
      "notes": "З Масюковщина, прибытие 19:57 (21 мин). Cmf ⚡2 ОТКРЫТ. Электро ⚡2.1, К+ ⚡2.2, Биз ⚡2.8." },

    { "id": "9925", "from": "Максима Богдановича 70", "to": "Корженевского 20к1",
      "factE": 21.7, "factC": 24.3, "yaSurgeC": 2.5, "yaMin": 26, "hour": 19,
      "notes": "Ю Сеница (на МКАД), прибытие 19:59 (26 мин). Cmf ⚡2.5 ОТКРЫТ. Электро ⚡2.5, К+ ⚡2.6, Биз ⚡3.6. Дальняя дальняя точка." },

    { "id": "9926", "from": "Максима Богдановича 70", "to": "Красноармейская 34Б",
      "factE": 12.0, "factC": 13.2, "yaSurgeC": 1.4, "yaMin": 13, "hour": 19,
      "notes": "Ю в центр, прибытие 19:48 (13 мин). Cmf ⚡1.4 ОТКРЫТ. Электро ⚡1.4, К+ ⚡1.4, Биз ⚡1.6." },

    { "id": "9927", "from": "Максима Богдановича 70", "to": "Коржа 16",
      "factE": 14.1, "factC": 15.7, "yaSurgeC": 1.6, "yaMin": 15, "hour": 19,
      "notes": "ЮЗ через Немигу, прибытие 19:50 (15 мин). Cmf ⚡1.6 ОТКРЫТ. Электро ⚡1.6, К+ ⚡1.7, Биз ⚡2.1." }
  ]
}
